drs_id_mongo_publisher/__init__.py
drs_id_mongo_publisher/healthcheck.py
drs_id_mongo_publisher/main.py
drs_id_mongo_publisher/runner.py
drs_id_mongo_publisher/model/obj_description.py
drs_id_mongo_publisher/utils/utils_db.py
drs_id_mongo_publisher/utils/utils_env.py
drs_id_mongo_publisher/utils/utils_mongo.py
drs_id_mongo_publisher-0.1.0.dist-info/METADATA
drs_id_mongo_publisher-0.1.0.dist-info/WHEEL
drs_id_mongo_publisher-0.1.0.dist-info/RECORD
