Metadata-Version: 2.4
Name: drs-id-mongo-publisher
Version: 0.1.0
Summary: A utility for populating Mongo with DRS Object records
Requires-Python: >=3.12
Requires-Dist: flake8>=7.1.2
Requires-Dist: oracledb>=3.0.0
Requires-Dist: pymongo>=4.11.2
Requires-Dist: pytest>=8.3.5
Requires-Dist: python-dotenv>=1.0.1
